robotframework_logs/__init__.py
robotframework_logs-0.1.0.dist-info/LICENSE
robotframework_logs-0.1.0.dist-info/METADATA
robotframework_logs-0.1.0.dist-info/WHEEL
robotframework_logs-0.1.0.dist-info/top_level.txt
robotframework_logs-0.1.0.dist-info/RECORD
