Metadata-Version: 2.1
Name: robotframework-logs
Version: 0.1.0
Summary: A client package for handling Robot Framework logs
Home-page: https://github.com/mkorpela/robotframework-logs
Author: Mikko Korpela
Author-email: mikko.korpela@gmail.com
Classifier: Programming Language :: Python :: 3
Classifier: License :: OSI Approved :: Apache Software License
Classifier: Operating System :: OS Independent
Requires-Python: >=3.6
License-File: LICENSE
